data_samples_printer/__init__.py
data_samples_printer/making_histograms.py
data_samples_printer/printing_histograms.py
data_samples_printer/py.typed
data_samples_printer-0.0.1.dist-info/METADATA
data_samples_printer-0.0.1.dist-info/WHEEL
data_samples_printer-0.0.1.dist-info/RECORD
