Metadata-Version: 2.1
Name: data-samples-printer
Version: 0.0.1
Summary: Don't be just mean and standart, print histograms as unicode instead!
Home-page: https://ernestum.github.io/data-samples-printer
License: MIT
Author: Maximilian Ernestus
Author-email: maximilian@ernestus.de
Requires-Python: >=3.8,<4.0
Classifier: Development Status :: 4 - Beta
Classifier: Intended Audience :: Developers
Classifier: License :: OSI Approved :: MIT License
Classifier: Operating System :: OS Independent
Classifier: Programming Language :: Python
Classifier: Programming Language :: Python :: 3
Classifier: Programming Language :: Python :: 3.8
Classifier: Programming Language :: Python :: 3.9
Classifier: Programming Language :: Python :: 3.10
Classifier: Programming Language :: Python :: 3.11
Classifier: Programming Language :: Python :: 3.7
Classifier: Topic :: Software Development :: Libraries :: Python Modules
Classifier: Typing :: Typed
Requires-Dist: numpy (>=1.19.5,<1.20.0) ; python_version == "3.6"
Requires-Dist: numpy (>=1.21.6,<1.22.0) ; python_version == "3.7"
Requires-Dist: numpy ; python_version >= "3.8" and python_version < "4.0"
Project-URL: Documentation, https://ernestum.github.io/data-samples-printer
Project-URL: Repository, https://github.com/ernestum/data-samples-printer
